appsearch/__init__.py
appsearch/forms.py
appsearch/models.py
appsearch/ormutils.py
appsearch/registry.py
appsearch/tests.py
appsearch/utils.py
appsearch/views.py
appsearch/static/js/jquery.appsearch.js
appsearch/static/js/jquery.appsearch.min.js
appsearch/templates/appsearch/default_form.html
appsearch/templates/appsearch/results_list.html
appsearch/templates/appsearch/search_form.html
django_appsearch-1.1.5.dist-info/LICENSE.txt
django_appsearch-1.1.5.dist-info/METADATA
django_appsearch-1.1.5.dist-info/WHEEL
django_appsearch-1.1.5.dist-info/top_level.txt
django_appsearch-1.1.5.dist-info/RECORD
