Metadata-Version: 2.1
Name: django-appsearch
Version: 1.1.5
Summary: Framework and generic app for cross-model searches on a single page
Home-page: https://github.com/pivotal-energy-solutions/django-appsearch
Author: Pivotal Energy Solutions
Author-email: tvalenta@pivotalenergysolutions.com
License: UNKNOWN
Download-URL: https://github.com/pivotal-energy-solutions/django-appsearch/archive/1.1.5.tar.gz
Project-URL: Source, https://github.com/pivotal-energy-solutions/django-appsearch
Project-URL: Bug Reports, https://github.com/pivotal-energy-solutions/django-appsearch/issues
Project-URL: Say Thanks!, http://saythanks.io/to/rh0dium
Keywords: django search
Platform: UNKNOWN
Classifier: Development Status :: 5 - Production/Stable
Classifier: Environment :: Web Environment
Classifier: Framework :: Django
Classifier: License :: OSI Approved :: Apache Software License
Classifier: Programming Language :: Python :: 2
Classifier: Programming Language :: Python :: 2.7
Classifier: Topic :: Internet :: WWW/HTTP
Classifier: Topic :: Internet :: WWW/HTTP :: Dynamic Content
Classifier: Topic :: Software Development :: Libraries :: Python Modules
Requires-Dist: django (<2.0,>=1.11)
